sim_metrics/__init__.py
sim_metrics/elmwise.py
sim_metrics/version.py
sim_metrics-1.0.0.dist-info/AUTHORS.rst
sim_metrics-1.0.0.dist-info/LICENSE
sim_metrics-1.0.0.dist-info/METADATA
sim_metrics-1.0.0.dist-info/WHEEL
sim_metrics-1.0.0.dist-info/top_level.txt
sim_metrics-1.0.0.dist-info/RECORD
