Metadata-Version: 1.1
Name: sim_metrics
Version: 1.0.0
Summary: Set of metrics for evaluating simulation results
Home-page: https://gitlab.com/revesansparole/sim_metrics
Author: revesansparole
Author-email: revesansparole@gmail.com
License: cc_by_nc
Platform: UNKNOWN
Classifier: Development Status :: 2 - Pre-Alpha
Classifier: Intended Audience :: Developers
Classifier: License :: OSI Approved :: BSD License
Classifier: Natural Language :: English
Classifier: Programming Language :: Python
Classifier: Programming Language :: Python :: 3
Classifier: Programming Language :: Python :: 3 :: Only
Classifier: Programming Language :: Python :: 3.7
Classifier: Programming Language :: Python :: 3.8
Classifier: Programming Language :: Python :: 3.9
